pytz-stubs/METADATA.toml
pytz-stubs/__init__.pyi
pytz-stubs/exceptions.pyi
pytz-stubs/lazy.pyi
pytz-stubs/reference.pyi
pytz-stubs/tzfile.pyi
pytz-stubs/tzinfo.pyi
types_pytz-2023.3.1.0.dist-info/METADATA
types_pytz-2023.3.1.0.dist-info/WHEEL
types_pytz-2023.3.1.0.dist-info/top_level.txt
types_pytz-2023.3.1.0.dist-info/RECORD
